{"nodes": [{"id": "c_users_rabin_documents_alsadeal_master_ecc_docs_zh_cn_rules_csharp_testing_md", "label": "testing.md", "file_type": "document", "source_file": "ECC/docs/zh-CN/rules/csharp/testing.md", "source_location": "L1"}, {"id": "csharp_testing_c_\u6d4b\u8bd5", "label": "C# \u6d4b\u8bd5", "file_type": "document", "source_file": "ECC/docs/zh-CN/rules/csharp/testing.md", "source_location": "L8"}, {"id": "csharp_testing_\u6d4b\u8bd5\u6846\u67b6", "label": "\u6d4b\u8bd5\u6846\u67b6", "file_type": "document", "source_file": "ECC/docs/zh-CN/rules/csharp/testing.md", "source_location": "L12"}, {"id": "csharp_testing_\u6d4b\u8bd5\u7ec4\u7ec7", "label": "\u6d4b\u8bd5\u7ec4\u7ec7", "file_type": "document", "source_file": "ECC/docs/zh-CN/rules/csharp/testing.md", "source_location": "L19"}, {"id": "csharp_testing_asp_net_core_\u96c6\u6210\u6d4b\u8bd5", "label": "ASP.NET Core \u96c6\u6210\u6d4b\u8bd5", "file_type": "document", "source_file": "ECC/docs/zh-CN/rules/csharp/testing.md", "source_location": "L38"}, {"id": "csharp_testing_\u8986\u76d6\u7387", "label": "\u8986\u76d6\u7387", "file_type": "document", "source_file": "ECC/docs/zh-CN/rules/csharp/testing.md", "source_location": "L43"}], "edges": [{"source": "c_users_rabin_documents_alsadeal_master_ecc_docs_zh_cn_rules_csharp_testing_md", "target": "csharp_testing_c_\u6d4b\u8bd5", "relation": "contains", "confidence": "EXTRACTED", "source_file": "ECC/docs/zh-CN/rules/csharp/testing.md", "source_location": "L8", "weight": 1.0}, {"source": "csharp_testing_c_\u6d4b\u8bd5", "target": "csharp_testing_\u6d4b\u8bd5\u6846\u67b6", "relation": "contains", "confidence": "EXTRACTED", "source_file": "ECC/docs/zh-CN/rules/csharp/testing.md", "source_location": "L12", "weight": 1.0}, {"source": "csharp_testing_c_\u6d4b\u8bd5", "target": "csharp_testing_\u6d4b\u8bd5\u7ec4\u7ec7", "relation": "contains", "confidence": "EXTRACTED", "source_file": "ECC/docs/zh-CN/rules/csharp/testing.md", "source_location": "L19", "weight": 1.0}, {"source": "csharp_testing_c_\u6d4b\u8bd5", "target": "csharp_testing_asp_net_core_\u96c6\u6210\u6d4b\u8bd5", "relation": "contains", "confidence": "EXTRACTED", "source_file": "ECC/docs/zh-CN/rules/csharp/testing.md", "source_location": "L38", "weight": 1.0}, {"source": "csharp_testing_c_\u6d4b\u8bd5", "target": "csharp_testing_\u8986\u76d6\u7387", "relation": "contains", "confidence": "EXTRACTED", "source_file": "ECC/docs/zh-CN/rules/csharp/testing.md", "source_location": "L43", "weight": 1.0}], "input_tokens": 0, "output_tokens": 0}