{"nodes": [{"id": "c_users_rabin_documents_alsadeal_master_ecc_docs_ja_jp_skills_terminal_ops_skill_md", "label": "SKILL.md", "file_type": "document", "source_file": "ECC/docs/ja-JP/skills/terminal-ops/SKILL.md", "source_location": "L1"}, {"id": "terminal_ops_skill_\u30bf\u30fc\u30df\u30ca\u30eb\u30aa\u30da\u30ec\u30fc\u30b7\u30e7\u30f3", "label": "\u30bf\u30fc\u30df\u30ca\u30eb\u30aa\u30da\u30ec\u30fc\u30b7\u30e7\u30f3", "file_type": "document", "source_file": "ECC/docs/ja-JP/skills/terminal-ops/SKILL.md", "source_location": "L7"}, {"id": "terminal_ops_skill_\u30b9\u30ad\u30eb\u30b9\u30bf\u30c3\u30af", "label": "\u30b9\u30ad\u30eb\u30b9\u30bf\u30c3\u30af", "file_type": "document", "source_file": "ECC/docs/ja-JP/skills/terminal-ops/SKILL.md", "source_location": "L13"}, {"id": "terminal_ops_skill_\u4f7f\u7528\u5834\u9762", "label": "\u4f7f\u7528\u5834\u9762", "file_type": "document", "source_file": "ECC/docs/ja-JP/skills/terminal-ops/SKILL.md", "source_location": "L23"}, {"id": "terminal_ops_skill_\u5b89\u5168\u7b56", "label": "\u5b89\u5168\u7b56", "file_type": "document", "source_file": "ECC/docs/ja-JP/skills/terminal-ops/SKILL.md", "source_location": "L29"}, {"id": "terminal_ops_skill_\u30ef\u30fc\u30af\u30d5\u30ed\u30fc", "label": "\u30ef\u30fc\u30af\u30d5\u30ed\u30fc", "file_type": "document", "source_file": "ECC/docs/ja-JP/skills/terminal-ops/SKILL.md", "source_location": "L37"}, {"id": "terminal_ops_skill_1_\u4f5c\u696d\u30b5\u30fc\u30d5\u30a7\u30b9\u3092\u7279\u5b9a\u3059\u308b", "label": "1. \u4f5c\u696d\u30b5\u30fc\u30d5\u30a7\u30b9\u3092\u7279\u5b9a\u3059\u308b", "file_type": "document", "source_file": "ECC/docs/ja-JP/skills/terminal-ops/SKILL.md", "source_location": "L39"}, {"id": "terminal_ops_skill_2_\u307e\u305a\u5931\u6557\u30b5\u30fc\u30d5\u30a7\u30b9\u3092\u8aad\u307f\u53d6\u308b", "label": "2. \u307e\u305a\u5931\u6557\u30b5\u30fc\u30d5\u30a7\u30b9\u3092\u8aad\u307f\u53d6\u308b", "file_type": "document", "source_file": "ECC/docs/ja-JP/skills/terminal-ops/SKILL.md", "source_location": "L52"}, {"id": "terminal_ops_skill_3_\u4fee\u6b63\u3092\u72ed\u3044\u7bc4\u56f2\u306b\u4fdd\u3064", "label": "3. \u4fee\u6b63\u3092\u72ed\u3044\u7bc4\u56f2\u306b\u4fdd\u3064", "file_type": "document", "source_file": "ECC/docs/ja-JP/skills/terminal-ops/SKILL.md", "source_location": "L61"}, {"id": "terminal_ops_skill_4_\u6b63\u78ba\u306a\u5b9f\u884c\u72b6\u614b\u3092\u30ec\u30dd\u30fc\u30c8\u3059\u308b", "label": "4. \u6b63\u78ba\u306a\u5b9f\u884c\u72b6\u614b\u3092\u30ec\u30dd\u30fc\u30c8\u3059\u308b", "file_type": "document", "source_file": "ECC/docs/ja-JP/skills/terminal-ops/SKILL.md", "source_location": "L69"}, {"id": "terminal_ops_skill_\u51fa\u529b\u30d5\u30a9\u30fc\u30de\u30c3\u30c8", "label": "\u51fa\u529b\u30d5\u30a9\u30fc\u30de\u30c3\u30c8", "file_type": "document", "source_file": "ECC/docs/ja-JP/skills/terminal-ops/SKILL.md", "source_location": "L80"}, {"id": "terminal_ops_skill_\u843d\u3068\u3057\u7a74", "label": "\u843d\u3068\u3057\u7a74", "file_type": "document", "source_file": "ECC/docs/ja-JP/skills/terminal-ops/SKILL.md", "source_location": "L98"}, {"id": "terminal_ops_skill_\u691c\u8a3c", "label": "\u691c\u8a3c", "file_type": "document", "source_file": "ECC/docs/ja-JP/skills/terminal-ops/SKILL.md", "source_location": "L105"}], "edges": [{"source": "c_users_rabin_documents_alsadeal_master_ecc_docs_ja_jp_skills_terminal_ops_skill_md", "target": "terminal_ops_skill_\u30bf\u30fc\u30df\u30ca\u30eb\u30aa\u30da\u30ec\u30fc\u30b7\u30e7\u30f3", "relation": "contains", "confidence": "EXTRACTED", "source_file": "ECC/docs/ja-JP/skills/terminal-ops/SKILL.md", "source_location": "L7", "weight": 1.0}, {"source": "terminal_ops_skill_\u30bf\u30fc\u30df\u30ca\u30eb\u30aa\u30da\u30ec\u30fc\u30b7\u30e7\u30f3", "target": "terminal_ops_skill_\u30b9\u30ad\u30eb\u30b9\u30bf\u30c3\u30af", "relation": "contains", "confidence": "EXTRACTED", "source_file": "ECC/docs/ja-JP/skills/terminal-ops/SKILL.md", "source_location": "L13", "weight": 1.0}, {"source": "terminal_ops_skill_\u30bf\u30fc\u30df\u30ca\u30eb\u30aa\u30da\u30ec\u30fc\u30b7\u30e7\u30f3", "target": "terminal_ops_skill_\u4f7f\u7528\u5834\u9762", "relation": "contains", "confidence": "EXTRACTED", "source_file": "ECC/docs/ja-JP/skills/terminal-ops/SKILL.md", "source_location": "L23", "weight": 1.0}, {"source": "terminal_ops_skill_\u30bf\u30fc\u30df\u30ca\u30eb\u30aa\u30da\u30ec\u30fc\u30b7\u30e7\u30f3", "target": "terminal_ops_skill_\u5b89\u5168\u7b56", "relation": "contains", "confidence": "EXTRACTED", "source_file": "ECC/docs/ja-JP/skills/terminal-ops/SKILL.md", "source_location": "L29", "weight": 1.0}, {"source": "terminal_ops_skill_\u30bf\u30fc\u30df\u30ca\u30eb\u30aa\u30da\u30ec\u30fc\u30b7\u30e7\u30f3", "target": "terminal_ops_skill_\u30ef\u30fc\u30af\u30d5\u30ed\u30fc", "relation": "contains", "confidence": "EXTRACTED", "source_file": "ECC/docs/ja-JP/skills/terminal-ops/SKILL.md", "source_location": "L37", "weight": 1.0}, {"source": "terminal_ops_skill_\u30ef\u30fc\u30af\u30d5\u30ed\u30fc", "target": "terminal_ops_skill_1_\u4f5c\u696d\u30b5\u30fc\u30d5\u30a7\u30b9\u3092\u7279\u5b9a\u3059\u308b", "relation": "contains", "confidence": "EXTRACTED", "source_file": "ECC/docs/ja-JP/skills/terminal-ops/SKILL.md", "source_location": "L39", "weight": 1.0}, {"source": "terminal_ops_skill_\u30ef\u30fc\u30af\u30d5\u30ed\u30fc", "target": "terminal_ops_skill_2_\u307e\u305a\u5931\u6557\u30b5\u30fc\u30d5\u30a7\u30b9\u3092\u8aad\u307f\u53d6\u308b", "relation": "contains", "confidence": "EXTRACTED", "source_file": "ECC/docs/ja-JP/skills/terminal-ops/SKILL.md", "source_location": "L52", "weight": 1.0}, {"source": "terminal_ops_skill_\u30ef\u30fc\u30af\u30d5\u30ed\u30fc", "target": "terminal_ops_skill_3_\u4fee\u6b63\u3092\u72ed\u3044\u7bc4\u56f2\u306b\u4fdd\u3064", "relation": "contains", "confidence": "EXTRACTED", "source_file": "ECC/docs/ja-JP/skills/terminal-ops/SKILL.md", "source_location": "L61", "weight": 1.0}, {"source": "terminal_ops_skill_\u30ef\u30fc\u30af\u30d5\u30ed\u30fc", "target": "terminal_ops_skill_4_\u6b63\u78ba\u306a\u5b9f\u884c\u72b6\u614b\u3092\u30ec\u30dd\u30fc\u30c8\u3059\u308b", "relation": "contains", "confidence": "EXTRACTED", "source_file": "ECC/docs/ja-JP/skills/terminal-ops/SKILL.md", "source_location": "L69", "weight": 1.0}, {"source": "terminal_ops_skill_\u30bf\u30fc\u30df\u30ca\u30eb\u30aa\u30da\u30ec\u30fc\u30b7\u30e7\u30f3", "target": "terminal_ops_skill_\u51fa\u529b\u30d5\u30a9\u30fc\u30de\u30c3\u30c8", "relation": "contains", "confidence": "EXTRACTED", "source_file": "ECC/docs/ja-JP/skills/terminal-ops/SKILL.md", "source_location": "L80", "weight": 1.0}, {"source": "terminal_ops_skill_\u30bf\u30fc\u30df\u30ca\u30eb\u30aa\u30da\u30ec\u30fc\u30b7\u30e7\u30f3", "target": "terminal_ops_skill_\u843d\u3068\u3057\u7a74", "relation": "contains", "confidence": "EXTRACTED", "source_file": "ECC/docs/ja-JP/skills/terminal-ops/SKILL.md", "source_location": "L98", "weight": 1.0}, {"source": "terminal_ops_skill_\u30bf\u30fc\u30df\u30ca\u30eb\u30aa\u30da\u30ec\u30fc\u30b7\u30e7\u30f3", "target": "terminal_ops_skill_\u691c\u8a3c", "relation": "contains", "confidence": "EXTRACTED", "source_file": "ECC/docs/ja-JP/skills/terminal-ops/SKILL.md", "source_location": "L105", "weight": 1.0}], "input_tokens": 0, "output_tokens": 0}