{"nodes": [{"id": "c_users_rabin_documents_alsadeal_master_ecc_docs_ja_jp_rules_cpp_coding_style_md", "label": "coding-style.md", "file_type": "document", "source_file": "ECC/docs/ja-JP/rules/cpp/coding-style.md", "source_location": "L1"}, {"id": "cpp_coding_style_c_\u30b3\u30fc\u30c7\u30a3\u30f3\u30b0\u30b9\u30bf\u30a4\u30eb", "label": "C++ \u30b3\u30fc\u30c7\u30a3\u30f3\u30b0\u30b9\u30bf\u30a4\u30eb", "file_type": "document", "source_file": "ECC/docs/ja-JP/rules/cpp/coding-style.md", "source_location": "L11"}, {"id": "cpp_coding_style_\u30e2\u30c0\u30f3_c_c_17_20_23", "label": "\u30e2\u30c0\u30f3 C++\uff08C++17/20/23\uff09", "file_type": "document", "source_file": "ECC/docs/ja-JP/rules/cpp/coding-style.md", "source_location": "L15"}, {"id": "cpp_coding_style_\u30ea\u30bd\u30fc\u30b9\u7ba1\u7406", "label": "\u30ea\u30bd\u30fc\u30b9\u7ba1\u7406", "file_type": "document", "source_file": "ECC/docs/ja-JP/rules/cpp/coding-style.md", "source_location": "L22"}, {"id": "cpp_coding_style_\u547d\u540d\u898f\u5247", "label": "\u547d\u540d\u898f\u5247", "file_type": "document", "source_file": "ECC/docs/ja-JP/rules/cpp/coding-style.md", "source_location": "L29"}, {"id": "cpp_coding_style_\u30d5\u30a9\u30fc\u30de\u30c3\u30c8", "label": "\u30d5\u30a9\u30fc\u30de\u30c3\u30c8", "file_type": "document", "source_file": "ECC/docs/ja-JP/rules/cpp/coding-style.md", "source_location": "L37"}, {"id": "cpp_coding_style_\u53c2\u8003", "label": "\u53c2\u8003", "file_type": "document", "source_file": "ECC/docs/ja-JP/rules/cpp/coding-style.md", "source_location": "L42"}], "edges": [{"source": "c_users_rabin_documents_alsadeal_master_ecc_docs_ja_jp_rules_cpp_coding_style_md", "target": "cpp_coding_style_c_\u30b3\u30fc\u30c7\u30a3\u30f3\u30b0\u30b9\u30bf\u30a4\u30eb", "relation": "contains", "confidence": "EXTRACTED", "source_file": "ECC/docs/ja-JP/rules/cpp/coding-style.md", "source_location": "L11", "weight": 1.0}, {"source": "cpp_coding_style_c_\u30b3\u30fc\u30c7\u30a3\u30f3\u30b0\u30b9\u30bf\u30a4\u30eb", "target": "cpp_coding_style_\u30e2\u30c0\u30f3_c_c_17_20_23", "relation": "contains", "confidence": "EXTRACTED", "source_file": "ECC/docs/ja-JP/rules/cpp/coding-style.md", "source_location": "L15", "weight": 1.0}, {"source": "cpp_coding_style_c_\u30b3\u30fc\u30c7\u30a3\u30f3\u30b0\u30b9\u30bf\u30a4\u30eb", "target": "cpp_coding_style_\u30ea\u30bd\u30fc\u30b9\u7ba1\u7406", "relation": "contains", "confidence": "EXTRACTED", "source_file": "ECC/docs/ja-JP/rules/cpp/coding-style.md", "source_location": "L22", "weight": 1.0}, {"source": "cpp_coding_style_c_\u30b3\u30fc\u30c7\u30a3\u30f3\u30b0\u30b9\u30bf\u30a4\u30eb", "target": "cpp_coding_style_\u547d\u540d\u898f\u5247", "relation": "contains", "confidence": "EXTRACTED", "source_file": "ECC/docs/ja-JP/rules/cpp/coding-style.md", "source_location": "L29", "weight": 1.0}, {"source": "cpp_coding_style_c_\u30b3\u30fc\u30c7\u30a3\u30f3\u30b0\u30b9\u30bf\u30a4\u30eb", "target": "cpp_coding_style_\u30d5\u30a9\u30fc\u30de\u30c3\u30c8", "relation": "contains", "confidence": "EXTRACTED", "source_file": "ECC/docs/ja-JP/rules/cpp/coding-style.md", "source_location": "L37", "weight": 1.0}, {"source": "cpp_coding_style_c_\u30b3\u30fc\u30c7\u30a3\u30f3\u30b0\u30b9\u30bf\u30a4\u30eb", "target": "cpp_coding_style_\u53c2\u8003", "relation": "contains", "confidence": "EXTRACTED", "source_file": "ECC/docs/ja-JP/rules/cpp/coding-style.md", "source_location": "L42", "weight": 1.0}], "input_tokens": 0, "output_tokens": 0}