{"nodes": [{"id": "c_users_rabin_documents_alsadeal_master_ecc_docs_tr_commands_e2e_md", "label": "e2e.md", "file_type": "document", "source_file": "ECC/docs/tr/commands/e2e.md", "source_location": "L1"}, {"id": "commands_e2e_e2e_komutu", "label": "E2E Komutu", "file_type": "document", "source_file": "ECC/docs/tr/commands/e2e.md", "source_location": "L5"}, {"id": "commands_e2e_bu_komut_ne_yapar", "label": "Bu Komut Ne Yapar", "file_type": "document", "source_file": "ECC/docs/tr/commands/e2e.md", "source_location": "L9"}, {"id": "commands_e2e_ne_zaman_kullan\u0131l\u0131r", "label": "Ne Zaman Kullan\u0131l\u0131r", "file_type": "document", "source_file": "ECC/docs/tr/commands/e2e.md", "source_location": "L17"}, {"id": "commands_e2e_nas\u0131l_\u00e7al\u0131\u015f\u0131r", "label": "Nas\u0131l \u00c7al\u0131\u015f\u0131r", "file_type": "document", "source_file": "ECC/docs/tr/commands/e2e.md", "source_location": "L26"}, {"id": "commands_e2e_\u00f6rnek_kullan\u0131m", "label": "\u00d6rnek Kullan\u0131m", "file_type": "document", "source_file": "ECC/docs/tr/commands/e2e.md", "source_location": "L37"}, {"id": "commands_e2e_olu\u015fturulan_testi_\u00e7al\u0131\u015ft\u0131r", "label": "Olu\u015fturulan testi \u00e7al\u0131\u015ft\u0131r", "file_type": "document", "source_file": "ECC/docs/tr/commands/e2e.md", "source_location": "L162"}, {"id": "commands_e2e_test_artifact_lar\u0131", "label": "Test Artifact'lar\u0131", "file_type": "document", "source_file": "ECC/docs/tr/commands/e2e.md", "source_location": "L205"}, {"id": "commands_e2e_artifact_lar\u0131_g\u00f6r\u00fcnt\u00fcleme", "label": "Artifact'lar\u0131 G\u00f6r\u00fcnt\u00fcleme", "file_type": "document", "source_file": "ECC/docs/tr/commands/e2e.md", "source_location": "L220"}, {"id": "commands_e2e_dengesiz_test_tespiti", "label": "Dengesiz Test Tespiti", "file_type": "document", "source_file": "ECC/docs/tr/commands/e2e.md", "source_location": "L233"}, {"id": "commands_e2e_taray\u0131c\u0131_yap\u0131land\u0131rmas\u0131", "label": "Taray\u0131c\u0131 Yap\u0131land\u0131rmas\u0131", "file_type": "document", "source_file": "ECC/docs/tr/commands/e2e.md", "source_location": "L254"}, {"id": "commands_e2e_ci_cd_entegrasyonu", "label": "CI/CD Entegrasyonu", "file_type": "document", "source_file": "ECC/docs/tr/commands/e2e.md", "source_location": "L264"}, {"id": "commands_e2e_pmx_e_\u00f6zg\u00fc_kritik_ak\u0131\u015flar", "label": "PMX'e \u00d6zg\u00fc Kritik Ak\u0131\u015flar", "file_type": "document", "source_file": "ECC/docs/tr/commands/e2e.md", "source_location": "L284"}, {"id": "commands_e2e_en_i\u0307yi_uygulamalar", "label": "En \u0130yi Uygulamalar", "file_type": "document", "source_file": "ECC/docs/tr/commands/e2e.md", "source_location": "L305"}, {"id": "commands_e2e_\u00f6nemli_notlar", "label": "\u00d6nemli Notlar", "file_type": "document", "source_file": "ECC/docs/tr/commands/e2e.md", "source_location": "L323"}, {"id": "commands_e2e_di\u011fer_komutlarla_entegrasyon", "label": "Di\u011fer Komutlarla Entegrasyon", "file_type": "document", "source_file": "ECC/docs/tr/commands/e2e.md", "source_location": "L331"}, {"id": "commands_e2e_i\u0307lgili_agent_lar", "label": "\u0130lgili Agent'lar", "file_type": "document", "source_file": "ECC/docs/tr/commands/e2e.md", "source_location": "L338"}, {"id": "commands_e2e_h\u0131zl\u0131_komutlar", "label": "H\u0131zl\u0131 Komutlar", "file_type": "document", "source_file": "ECC/docs/tr/commands/e2e.md", "source_location": "L345"}], "edges": [{"source": "c_users_rabin_documents_alsadeal_master_ecc_docs_tr_commands_e2e_md", "target": "commands_e2e_e2e_komutu", "relation": "contains", "confidence": "EXTRACTED", "source_file": "ECC/docs/tr/commands/e2e.md", "source_location": "L5", "weight": 1.0}, {"source": "commands_e2e_e2e_komutu", "target": "commands_e2e_bu_komut_ne_yapar", "relation": "contains", "confidence": "EXTRACTED", "source_file": "ECC/docs/tr/commands/e2e.md", "source_location": "L9", "weight": 1.0}, {"source": "commands_e2e_e2e_komutu", "target": "commands_e2e_ne_zaman_kullan\u0131l\u0131r", "relation": "contains", "confidence": "EXTRACTED", "source_file": "ECC/docs/tr/commands/e2e.md", "source_location": "L17", "weight": 1.0}, {"source": "commands_e2e_e2e_komutu", "target": "commands_e2e_nas\u0131l_\u00e7al\u0131\u015f\u0131r", "relation": "contains", "confidence": "EXTRACTED", "source_file": "ECC/docs/tr/commands/e2e.md", "source_location": "L26", "weight": 1.0}, {"source": "commands_e2e_e2e_komutu", "target": "commands_e2e_\u00f6rnek_kullan\u0131m", "relation": "contains", "confidence": "EXTRACTED", "source_file": "ECC/docs/tr/commands/e2e.md", "source_location": "L37", "weight": 1.0}, {"source": "c_users_rabin_documents_alsadeal_master_ecc_docs_tr_commands_e2e_md", "target": "commands_e2e_olu\u015fturulan_testi_\u00e7al\u0131\u015ft\u0131r", "relation": "contains", "confidence": "EXTRACTED", "source_file": "ECC/docs/tr/commands/e2e.md", "source_location": "L162", "weight": 1.0}, {"source": "commands_e2e_olu\u015fturulan_testi_\u00e7al\u0131\u015ft\u0131r", "target": "commands_e2e_test_artifact_lar\u0131", "relation": "contains", "confidence": "EXTRACTED", "source_file": "ECC/docs/tr/commands/e2e.md", "source_location": "L205", "weight": 1.0}, {"source": "commands_e2e_olu\u015fturulan_testi_\u00e7al\u0131\u015ft\u0131r", "target": "commands_e2e_artifact_lar\u0131_g\u00f6r\u00fcnt\u00fcleme", "relation": "contains", "confidence": "EXTRACTED", "source_file": "ECC/docs/tr/commands/e2e.md", "source_location": "L220", "weight": 1.0}, {"source": "commands_e2e_olu\u015fturulan_testi_\u00e7al\u0131\u015ft\u0131r", "target": "commands_e2e_dengesiz_test_tespiti", "relation": "contains", "confidence": "EXTRACTED", "source_file": "ECC/docs/tr/commands/e2e.md", "source_location": "L233", "weight": 1.0}, {"source": "commands_e2e_olu\u015fturulan_testi_\u00e7al\u0131\u015ft\u0131r", "target": "commands_e2e_taray\u0131c\u0131_yap\u0131land\u0131rmas\u0131", "relation": "contains", "confidence": "EXTRACTED", "source_file": "ECC/docs/tr/commands/e2e.md", "source_location": "L254", "weight": 1.0}, {"source": "commands_e2e_olu\u015fturulan_testi_\u00e7al\u0131\u015ft\u0131r", "target": "commands_e2e_ci_cd_entegrasyonu", "relation": "contains", "confidence": "EXTRACTED", "source_file": "ECC/docs/tr/commands/e2e.md", "source_location": "L264", "weight": 1.0}, {"source": "commands_e2e_olu\u015fturulan_testi_\u00e7al\u0131\u015ft\u0131r", "target": "commands_e2e_pmx_e_\u00f6zg\u00fc_kritik_ak\u0131\u015flar", "relation": "contains", "confidence": "EXTRACTED", "source_file": "ECC/docs/tr/commands/e2e.md", "source_location": "L284", "weight": 1.0}, {"source": "commands_e2e_olu\u015fturulan_testi_\u00e7al\u0131\u015ft\u0131r", "target": "commands_e2e_en_i\u0307yi_uygulamalar", "relation": "contains", "confidence": "EXTRACTED", "source_file": "ECC/docs/tr/commands/e2e.md", "source_location": "L305", "weight": 1.0}, {"source": "commands_e2e_olu\u015fturulan_testi_\u00e7al\u0131\u015ft\u0131r", "target": "commands_e2e_\u00f6nemli_notlar", "relation": "contains", "confidence": "EXTRACTED", "source_file": "ECC/docs/tr/commands/e2e.md", "source_location": "L323", "weight": 1.0}, {"source": "commands_e2e_olu\u015fturulan_testi_\u00e7al\u0131\u015ft\u0131r", "target": "commands_e2e_di\u011fer_komutlarla_entegrasyon", "relation": "contains", "confidence": "EXTRACTED", "source_file": "ECC/docs/tr/commands/e2e.md", "source_location": "L331", "weight": 1.0}, {"source": "commands_e2e_olu\u015fturulan_testi_\u00e7al\u0131\u015ft\u0131r", "target": "commands_e2e_i\u0307lgili_agent_lar", "relation": "contains", "confidence": "EXTRACTED", "source_file": "ECC/docs/tr/commands/e2e.md", "source_location": "L338", "weight": 1.0}, {"source": "commands_e2e_olu\u015fturulan_testi_\u00e7al\u0131\u015ft\u0131r", "target": "commands_e2e_h\u0131zl\u0131_komutlar", "relation": "contains", "confidence": "EXTRACTED", "source_file": "ECC/docs/tr/commands/e2e.md", "source_location": "L345", "weight": 1.0}], "input_tokens": 0, "output_tokens": 0}