{"nodes": [{"id": "c_users_rabin_documents_alsadeal_master_ecc_changelog_md", "label": "CHANGELOG.md", "file_type": "document", "source_file": "ECC/CHANGELOG.md", "source_location": "L1"}, {"id": "ecc_changelog_changelog", "label": "Changelog", "file_type": "document", "source_file": "ECC/CHANGELOG.md", "source_location": "L1"}, {"id": "ecc_changelog_2_0_0_rc_1_2026_04_28", "label": "2.0.0-rc.1 - 2026-04-28", "file_type": "document", "source_file": "ECC/CHANGELOG.md", "source_location": "L3"}, {"id": "ecc_changelog_highlights", "label": "Highlights", "file_type": "document", "source_file": "ECC/CHANGELOG.md", "source_location": "L5"}, {"id": "ecc_changelog_release_surface", "label": "Release Surface", "file_type": "document", "source_file": "ECC/CHANGELOG.md", "source_location": "L11"}, {"id": "ecc_changelog_notes", "label": "Notes", "file_type": "document", "source_file": "ECC/CHANGELOG.md", "source_location": "L18"}, {"id": "ecc_changelog_1_10_0_2026_04_05", "label": "1.10.0 - 2026-04-05", "file_type": "document", "source_file": "ECC/CHANGELOG.md", "source_location": "L23"}, {"id": "ecc_changelog_highlights_25", "label": "Highlights", "file_type": "document", "source_file": "ECC/CHANGELOG.md", "source_location": "L25"}, {"id": "ecc_changelog_release_surface_32", "label": "Release Surface", "file_type": "document", "source_file": "ECC/CHANGELOG.md", "source_location": "L32"}, {"id": "ecc_changelog_new_workflow_lanes", "label": "New Workflow Lanes", "file_type": "document", "source_file": "ECC/CHANGELOG.md", "source_location": "L38"}, {"id": "ecc_changelog_ecc_2_0_alpha", "label": "ECC 2.0 Alpha", "file_type": "document", "source_file": "ECC/CHANGELOG.md", "source_location": "L46"}, {"id": "ecc_changelog_notes_52", "label": "Notes", "file_type": "document", "source_file": "ECC/CHANGELOG.md", "source_location": "L52"}, {"id": "ecc_changelog_1_9_0_2026_03_20", "label": "1.9.0 - 2026-03-20", "file_type": "document", "source_file": "ECC/CHANGELOG.md", "source_location": "L57"}, {"id": "ecc_changelog_highlights_59", "label": "Highlights", "file_type": "document", "source_file": "ECC/CHANGELOG.md", "source_location": "L59"}, {"id": "ecc_changelog_new_agents", "label": "New Agents", "file_type": "document", "source_file": "ECC/CHANGELOG.md", "source_location": "L66"}, {"id": "ecc_changelog_new_skills", "label": "New Skills", "file_type": "document", "source_file": "ECC/CHANGELOG.md", "source_location": "L78"}, {"id": "ecc_changelog_new_commands", "label": "New Commands", "file_type": "document", "source_file": "ECC/CHANGELOG.md", "source_location": "L96"}, {"id": "ecc_changelog_new_rules", "label": "New Rules", "file_type": "document", "source_file": "ECC/CHANGELOG.md", "source_location": "L104"}, {"id": "ecc_changelog_infrastructure", "label": "Infrastructure", "file_type": "document", "source_file": "ECC/CHANGELOG.md", "source_location": "L113"}, {"id": "ecc_changelog_bug_fixes", "label": "Bug Fixes", "file_type": "document", "source_file": "ECC/CHANGELOG.md", "source_location": "L126"}, {"id": "ecc_changelog_translations", "label": "Translations", "file_type": "document", "source_file": "ECC/CHANGELOG.md", "source_location": "L142"}, {"id": "ecc_changelog_credits", "label": "Credits", "file_type": "document", "source_file": "ECC/CHANGELOG.md", "source_location": "L147"}, {"id": "ecc_changelog_1_8_0_2026_03_04", "label": "1.8.0 - 2026-03-04", "file_type": "document", "source_file": "ECC/CHANGELOG.md", "source_location": "L160"}, {"id": "ecc_changelog_highlights_162", "label": "Highlights", "file_type": "document", "source_file": "ECC/CHANGELOG.md", "source_location": "L162"}, {"id": "ecc_changelog_core", "label": "Core", "file_type": "document", "source_file": "ECC/CHANGELOG.md", "source_location": "L168"}, {"id": "ecc_changelog_hook_reliability", "label": "Hook Reliability", "file_type": "document", "source_file": "ECC/CHANGELOG.md", "source_location": "L183"}, {"id": "ecc_changelog_cross_platform", "label": "Cross-Platform", "file_type": "document", "source_file": "ECC/CHANGELOG.md", "source_location": "L191"}, {"id": "ecc_changelog_notes_196", "label": "Notes", "file_type": "document", "source_file": "ECC/CHANGELOG.md", "source_location": "L196"}, {"id": "ecc_changelog_credits_200", "label": "Credits", "file_type": "document", "source_file": "ECC/CHANGELOG.md", "source_location": "L200"}], "edges": [{"source": "c_users_rabin_documents_alsadeal_master_ecc_changelog_md", "target": "ecc_changelog_changelog", "relation": "contains", "confidence": "EXTRACTED", "source_file": "ECC/CHANGELOG.md", "source_location": "L1", "weight": 1.0}, {"source": "ecc_changelog_changelog", "target": "ecc_changelog_2_0_0_rc_1_2026_04_28", "relation": "contains", "confidence": "EXTRACTED", "source_file": "ECC/CHANGELOG.md", "source_location": "L3", "weight": 1.0}, {"source": "ecc_changelog_2_0_0_rc_1_2026_04_28", "target": "ecc_changelog_highlights", "relation": "contains", "confidence": "EXTRACTED", "source_file": "ECC/CHANGELOG.md", "source_location": "L5", "weight": 1.0}, {"source": "ecc_changelog_2_0_0_rc_1_2026_04_28", "target": "ecc_changelog_release_surface", "relation": "contains", "confidence": "EXTRACTED", "source_file": "ECC/CHANGELOG.md", "source_location": "L11", "weight": 1.0}, {"source": "ecc_changelog_2_0_0_rc_1_2026_04_28", "target": "ecc_changelog_notes", "relation": "contains", "confidence": "EXTRACTED", "source_file": "ECC/CHANGELOG.md", "source_location": "L18", "weight": 1.0}, {"source": "ecc_changelog_changelog", "target": "ecc_changelog_1_10_0_2026_04_05", "relation": "contains", "confidence": "EXTRACTED", "source_file": "ECC/CHANGELOG.md", "source_location": "L23", "weight": 1.0}, {"source": "ecc_changelog_1_10_0_2026_04_05", "target": "ecc_changelog_highlights_25", "relation": "contains", "confidence": "EXTRACTED", "source_file": "ECC/CHANGELOG.md", "source_location": "L25", "weight": 1.0}, {"source": "ecc_changelog_1_10_0_2026_04_05", "target": "ecc_changelog_release_surface_32", "relation": "contains", "confidence": "EXTRACTED", "source_file": "ECC/CHANGELOG.md", "source_location": "L32", "weight": 1.0}, {"source": "ecc_changelog_1_10_0_2026_04_05", "target": "ecc_changelog_new_workflow_lanes", "relation": "contains", "confidence": "EXTRACTED", "source_file": "ECC/CHANGELOG.md", "source_location": "L38", "weight": 1.0}, {"source": "ecc_changelog_1_10_0_2026_04_05", "target": "ecc_changelog_ecc_2_0_alpha", "relation": "contains", "confidence": "EXTRACTED", "source_file": "ECC/CHANGELOG.md", "source_location": "L46", "weight": 1.0}, {"source": "ecc_changelog_1_10_0_2026_04_05", "target": "ecc_changelog_notes_52", "relation": "contains", "confidence": "EXTRACTED", "source_file": "ECC/CHANGELOG.md", "source_location": "L52", "weight": 1.0}, {"source": "ecc_changelog_changelog", "target": "ecc_changelog_1_9_0_2026_03_20", "relation": "contains", "confidence": "EXTRACTED", "source_file": "ECC/CHANGELOG.md", "source_location": "L57", "weight": 1.0}, {"source": "ecc_changelog_1_9_0_2026_03_20", "target": "ecc_changelog_highlights_59", "relation": "contains", "confidence": "EXTRACTED", "source_file": "ECC/CHANGELOG.md", "source_location": "L59", "weight": 1.0}, {"source": "ecc_changelog_1_9_0_2026_03_20", "target": "ecc_changelog_new_agents", "relation": "contains", "confidence": "EXTRACTED", "source_file": "ECC/CHANGELOG.md", "source_location": "L66", "weight": 1.0}, {"source": "ecc_changelog_1_9_0_2026_03_20", "target": "ecc_changelog_new_skills", "relation": "contains", "confidence": "EXTRACTED", "source_file": "ECC/CHANGELOG.md", "source_location": "L78", "weight": 1.0}, {"source": "ecc_changelog_1_9_0_2026_03_20", "target": "ecc_changelog_new_commands", "relation": "contains", "confidence": "EXTRACTED", "source_file": "ECC/CHANGELOG.md", "source_location": "L96", "weight": 1.0}, {"source": "ecc_changelog_1_9_0_2026_03_20", "target": "ecc_changelog_new_rules", "relation": "contains", "confidence": "EXTRACTED", "source_file": "ECC/CHANGELOG.md", "source_location": "L104", "weight": 1.0}, {"source": "ecc_changelog_1_9_0_2026_03_20", "target": "ecc_changelog_infrastructure", "relation": "contains", "confidence": "EXTRACTED", "source_file": "ECC/CHANGELOG.md", "source_location": "L113", "weight": 1.0}, {"source": "ecc_changelog_1_9_0_2026_03_20", "target": "ecc_changelog_bug_fixes", "relation": "contains", "confidence": "EXTRACTED", "source_file": "ECC/CHANGELOG.md", "source_location": "L126", "weight": 1.0}, {"source": "ecc_changelog_1_9_0_2026_03_20", "target": "ecc_changelog_translations", "relation": "contains", "confidence": "EXTRACTED", "source_file": "ECC/CHANGELOG.md", "source_location": "L142", "weight": 1.0}, {"source": "ecc_changelog_1_9_0_2026_03_20", "target": "ecc_changelog_credits", "relation": "contains", "confidence": "EXTRACTED", "source_file": "ECC/CHANGELOG.md", "source_location": "L147", "weight": 1.0}, {"source": "ecc_changelog_changelog", "target": "ecc_changelog_1_8_0_2026_03_04", "relation": "contains", "confidence": "EXTRACTED", "source_file": "ECC/CHANGELOG.md", "source_location": "L160", "weight": 1.0}, {"source": "ecc_changelog_1_8_0_2026_03_04", "target": "ecc_changelog_highlights_162", "relation": "contains", "confidence": "EXTRACTED", "source_file": "ECC/CHANGELOG.md", "source_location": "L162", "weight": 1.0}, {"source": "ecc_changelog_1_8_0_2026_03_04", "target": "ecc_changelog_core", "relation": "contains", "confidence": "EXTRACTED", "source_file": "ECC/CHANGELOG.md", "source_location": "L168", "weight": 1.0}, {"source": "ecc_changelog_1_8_0_2026_03_04", "target": "ecc_changelog_hook_reliability", "relation": "contains", "confidence": "EXTRACTED", "source_file": "ECC/CHANGELOG.md", "source_location": "L183", "weight": 1.0}, {"source": "ecc_changelog_1_8_0_2026_03_04", "target": "ecc_changelog_cross_platform", "relation": "contains", "confidence": "EXTRACTED", "source_file": "ECC/CHANGELOG.md", "source_location": "L191", "weight": 1.0}, {"source": "ecc_changelog_1_8_0_2026_03_04", "target": "ecc_changelog_notes_196", "relation": "contains", "confidence": "EXTRACTED", "source_file": "ECC/CHANGELOG.md", "source_location": "L196", "weight": 1.0}, {"source": "ecc_changelog_1_8_0_2026_03_04", "target": "ecc_changelog_credits_200", "relation": "contains", "confidence": "EXTRACTED", "source_file": "ECC/CHANGELOG.md", "source_location": "L200", "weight": 1.0}], "input_tokens": 0, "output_tokens": 0}