{"nodes": [{"id": "c_users_rabin_documents_alsadeal_master_ecc_docs_ja_jp_rules_fsharp_testing_md", "label": "testing.md", "file_type": "document", "source_file": "ECC/docs/ja-JP/rules/fsharp/testing.md", "source_location": "L1"}, {"id": "fsharp_testing_f_\u30c6\u30b9\u30c8", "label": "F# \u30c6\u30b9\u30c8", "file_type": "document", "source_file": "ECC/docs/ja-JP/rules/fsharp/testing.md", "source_location": "L7"}, {"id": "fsharp_testing_\u30c6\u30b9\u30c8\u30d5\u30ec\u30fc\u30e0\u30ef\u30fc\u30af", "label": "\u30c6\u30b9\u30c8\u30d5\u30ec\u30fc\u30e0\u30ef\u30fc\u30af", "file_type": "document", "source_file": "ECC/docs/ja-JP/rules/fsharp/testing.md", "source_location": "L11"}, {"id": "fsharp_testing_\u30c6\u30b9\u30c8\u306e\u69cb\u6210", "label": "\u30c6\u30b9\u30c8\u306e\u69cb\u6210", "file_type": "document", "source_file": "ECC/docs/ja-JP/rules/fsharp/testing.md", "source_location": "L19"}, {"id": "fsharp_testing_fscheck_\u3092\u4f7f\u3063\u305f\u30d7\u30ed\u30d1\u30c6\u30a3\u30d9\u30fc\u30b9\u30c6\u30b9\u30c8", "label": "FsCheck \u3092\u4f7f\u3063\u305f\u30d7\u30ed\u30d1\u30c6\u30a3\u30d9\u30fc\u30b9\u30c6\u30b9\u30c8", "file_type": "document", "source_file": "ECC/docs/ja-JP/rules/fsharp/testing.md", "source_location": "L42"}, {"id": "fsharp_testing_asp_net_core_\u30a4\u30f3\u30c6\u30b0\u30ec\u30fc\u30b7\u30e7\u30f3\u30c6\u30b9\u30c8", "label": "ASP.NET Core \u30a4\u30f3\u30c6\u30b0\u30ec\u30fc\u30b7\u30e7\u30f3\u30c6\u30b9\u30c8", "file_type": "document", "source_file": "ECC/docs/ja-JP/rules/fsharp/testing.md", "source_location": "L53"}, {"id": "fsharp_testing_\u30ab\u30d0\u30ec\u30c3\u30b8", "label": "\u30ab\u30d0\u30ec\u30c3\u30b8", "file_type": "document", "source_file": "ECC/docs/ja-JP/rules/fsharp/testing.md", "source_location": "L58"}], "edges": [{"source": "c_users_rabin_documents_alsadeal_master_ecc_docs_ja_jp_rules_fsharp_testing_md", "target": "fsharp_testing_f_\u30c6\u30b9\u30c8", "relation": "contains", "confidence": "EXTRACTED", "source_file": "ECC/docs/ja-JP/rules/fsharp/testing.md", "source_location": "L7", "weight": 1.0}, {"source": "fsharp_testing_f_\u30c6\u30b9\u30c8", "target": "fsharp_testing_\u30c6\u30b9\u30c8\u30d5\u30ec\u30fc\u30e0\u30ef\u30fc\u30af", "relation": "contains", "confidence": "EXTRACTED", "source_file": "ECC/docs/ja-JP/rules/fsharp/testing.md", "source_location": "L11", "weight": 1.0}, {"source": "fsharp_testing_f_\u30c6\u30b9\u30c8", "target": "fsharp_testing_\u30c6\u30b9\u30c8\u306e\u69cb\u6210", "relation": "contains", "confidence": "EXTRACTED", "source_file": "ECC/docs/ja-JP/rules/fsharp/testing.md", "source_location": "L19", "weight": 1.0}, {"source": "fsharp_testing_f_\u30c6\u30b9\u30c8", "target": "fsharp_testing_fscheck_\u3092\u4f7f\u3063\u305f\u30d7\u30ed\u30d1\u30c6\u30a3\u30d9\u30fc\u30b9\u30c6\u30b9\u30c8", "relation": "contains", "confidence": "EXTRACTED", "source_file": "ECC/docs/ja-JP/rules/fsharp/testing.md", "source_location": "L42", "weight": 1.0}, {"source": "fsharp_testing_f_\u30c6\u30b9\u30c8", "target": "fsharp_testing_asp_net_core_\u30a4\u30f3\u30c6\u30b0\u30ec\u30fc\u30b7\u30e7\u30f3\u30c6\u30b9\u30c8", "relation": "contains", "confidence": "EXTRACTED", "source_file": "ECC/docs/ja-JP/rules/fsharp/testing.md", "source_location": "L53", "weight": 1.0}, {"source": "fsharp_testing_f_\u30c6\u30b9\u30c8", "target": "fsharp_testing_\u30ab\u30d0\u30ec\u30c3\u30b8", "relation": "contains", "confidence": "EXTRACTED", "source_file": "ECC/docs/ja-JP/rules/fsharp/testing.md", "source_location": "L58", "weight": 1.0}], "input_tokens": 0, "output_tokens": 0}