{"nodes": [{"id": "c_users_rabin_documents_alsadeal_master_ecc_docs_ja_jp_agents_code_architect_md", "label": "code-architect.md", "file_type": "document", "source_file": "ECC/docs/ja-JP/agents/code-architect.md", "source_location": "L1"}, {"id": "agents_code_architect_\u30d7\u30ed\u30f3\u30d7\u30c8\u9632\u5fa1\u30d9\u30fc\u30b9\u30e9\u30a4\u30f3", "label": "\u30d7\u30ed\u30f3\u30d7\u30c8\u9632\u5fa1\u30d9\u30fc\u30b9\u30e9\u30a4\u30f3", "file_type": "document", "source_file": "ECC/docs/ja-JP/agents/code-architect.md", "source_location": "L8"}, {"id": "agents_code_architect_\u30b3\u30fc\u30c9\u30a2\u30fc\u30ad\u30c6\u30af\u30c8\u30a8\u30fc\u30b8\u30a7\u30f3\u30c8", "label": "\u30b3\u30fc\u30c9\u30a2\u30fc\u30ad\u30c6\u30af\u30c8\u30a8\u30fc\u30b8\u30a7\u30f3\u30c8", "file_type": "document", "source_file": "ECC/docs/ja-JP/agents/code-architect.md", "source_location": "L17"}, {"id": "agents_code_architect_\u30d7\u30ed\u30bb\u30b9", "label": "\u30d7\u30ed\u30bb\u30b9", "file_type": "document", "source_file": "ECC/docs/ja-JP/agents/code-architect.md", "source_location": "L21"}, {"id": "agents_code_architect_1_\u30d1\u30bf\u30fc\u30f3\u5206\u6790", "label": "1. \u30d1\u30bf\u30fc\u30f3\u5206\u6790", "file_type": "document", "source_file": "ECC/docs/ja-JP/agents/code-architect.md", "source_location": "L23"}, {"id": "agents_code_architect_2_\u30a2\u30fc\u30ad\u30c6\u30af\u30c1\u30e3\u8a2d\u8a08", "label": "2. \u30a2\u30fc\u30ad\u30c6\u30af\u30c1\u30e3\u8a2d\u8a08", "file_type": "document", "source_file": "ECC/docs/ja-JP/agents/code-architect.md", "source_location": "L30"}, {"id": "agents_code_architect_3_\u5b9f\u88c5\u30d6\u30eb\u30fc\u30d7\u30ea\u30f3\u30c8", "label": "3. \u5b9f\u88c5\u30d6\u30eb\u30fc\u30d7\u30ea\u30f3\u30c8", "file_type": "document", "source_file": "ECC/docs/ja-JP/agents/code-architect.md", "source_location": "L36"}, {"id": "agents_code_architect_4_\u30d3\u30eb\u30c9\u30b7\u30fc\u30b1\u30f3\u30b9", "label": "4. \u30d3\u30eb\u30c9\u30b7\u30fc\u30b1\u30f3\u30b9", "file_type": "document", "source_file": "ECC/docs/ja-JP/agents/code-architect.md", "source_location": "L46"}, {"id": "agents_code_architect_\u51fa\u529b\u30d5\u30a9\u30fc\u30de\u30c3\u30c8", "label": "\u51fa\u529b\u30d5\u30a9\u30fc\u30de\u30c3\u30c8", "file_type": "document", "source_file": "ECC/docs/ja-JP/agents/code-architect.md", "source_location": "L57"}], "edges": [{"source": "c_users_rabin_documents_alsadeal_master_ecc_docs_ja_jp_agents_code_architect_md", "target": "agents_code_architect_\u30d7\u30ed\u30f3\u30d7\u30c8\u9632\u5fa1\u30d9\u30fc\u30b9\u30e9\u30a4\u30f3", "relation": "contains", "confidence": "EXTRACTED", "source_file": "ECC/docs/ja-JP/agents/code-architect.md", "source_location": "L8", "weight": 1.0}, {"source": "c_users_rabin_documents_alsadeal_master_ecc_docs_ja_jp_agents_code_architect_md", "target": "agents_code_architect_\u30b3\u30fc\u30c9\u30a2\u30fc\u30ad\u30c6\u30af\u30c8\u30a8\u30fc\u30b8\u30a7\u30f3\u30c8", "relation": "contains", "confidence": "EXTRACTED", "source_file": "ECC/docs/ja-JP/agents/code-architect.md", "source_location": "L17", "weight": 1.0}, {"source": "agents_code_architect_\u30b3\u30fc\u30c9\u30a2\u30fc\u30ad\u30c6\u30af\u30c8\u30a8\u30fc\u30b8\u30a7\u30f3\u30c8", "target": "agents_code_architect_\u30d7\u30ed\u30bb\u30b9", "relation": "contains", "confidence": "EXTRACTED", "source_file": "ECC/docs/ja-JP/agents/code-architect.md", "source_location": "L21", "weight": 1.0}, {"source": "agents_code_architect_\u30d7\u30ed\u30bb\u30b9", "target": "agents_code_architect_1_\u30d1\u30bf\u30fc\u30f3\u5206\u6790", "relation": "contains", "confidence": "EXTRACTED", "source_file": "ECC/docs/ja-JP/agents/code-architect.md", "source_location": "L23", "weight": 1.0}, {"source": "agents_code_architect_\u30d7\u30ed\u30bb\u30b9", "target": "agents_code_architect_2_\u30a2\u30fc\u30ad\u30c6\u30af\u30c1\u30e3\u8a2d\u8a08", "relation": "contains", "confidence": "EXTRACTED", "source_file": "ECC/docs/ja-JP/agents/code-architect.md", "source_location": "L30", "weight": 1.0}, {"source": "agents_code_architect_\u30d7\u30ed\u30bb\u30b9", "target": "agents_code_architect_3_\u5b9f\u88c5\u30d6\u30eb\u30fc\u30d7\u30ea\u30f3\u30c8", "relation": "contains", "confidence": "EXTRACTED", "source_file": "ECC/docs/ja-JP/agents/code-architect.md", "source_location": "L36", "weight": 1.0}, {"source": "agents_code_architect_\u30d7\u30ed\u30bb\u30b9", "target": "agents_code_architect_4_\u30d3\u30eb\u30c9\u30b7\u30fc\u30b1\u30f3\u30b9", "relation": "contains", "confidence": "EXTRACTED", "source_file": "ECC/docs/ja-JP/agents/code-architect.md", "source_location": "L46", "weight": 1.0}, {"source": "agents_code_architect_\u30b3\u30fc\u30c9\u30a2\u30fc\u30ad\u30c6\u30af\u30c8\u30a8\u30fc\u30b8\u30a7\u30f3\u30c8", "target": "agents_code_architect_\u51fa\u529b\u30d5\u30a9\u30fc\u30de\u30c3\u30c8", "relation": "contains", "confidence": "EXTRACTED", "source_file": "ECC/docs/ja-JP/agents/code-architect.md", "source_location": "L57", "weight": 1.0}], "input_tokens": 0, "output_tokens": 0}