{"nodes": [{"id": "c_users_rabin_documents_alsadeal_master_ecc_docs_zh_cn_skills_clickhouse_io_skill_md", "label": "SKILL.md", "file_type": "document", "source_file": "ECC/docs/zh-CN/skills/clickhouse-io/SKILL.md", "source_location": "L1"}, {"id": "clickhouse_io_skill_clickhouse_\u5206\u6790\u6a21\u5f0f", "label": "ClickHouse \u5206\u6790\u6a21\u5f0f", "file_type": "document", "source_file": "ECC/docs/zh-CN/skills/clickhouse-io/SKILL.md", "source_location": "L7"}, {"id": "clickhouse_io_skill_\u4f55\u65f6\u6fc0\u6d3b", "label": "\u4f55\u65f6\u6fc0\u6d3b", "file_type": "document", "source_file": "ECC/docs/zh-CN/skills/clickhouse-io/SKILL.md", "source_location": "L11"}, {"id": "clickhouse_io_skill_\u6982\u8ff0", "label": "\u6982\u8ff0", "file_type": "document", "source_file": "ECC/docs/zh-CN/skills/clickhouse-io/SKILL.md", "source_location": "L20"}, {"id": "clickhouse_io_skill_\u8868\u8bbe\u8ba1\u6a21\u5f0f", "label": "\u8868\u8bbe\u8ba1\u6a21\u5f0f", "file_type": "document", "source_file": "ECC/docs/zh-CN/skills/clickhouse-io/SKILL.md", "source_location": "L32"}, {"id": "clickhouse_io_skill_mergetree_\u5f15\u64ce_\u6700\u5e38\u7528", "label": "MergeTree \u5f15\u64ce (\u6700\u5e38\u7528)", "file_type": "document", "source_file": "ECC/docs/zh-CN/skills/clickhouse-io/SKILL.md", "source_location": "L34"}, {"id": "clickhouse_io_skill_replacingmergetree_\u53bb\u91cd", "label": "ReplacingMergeTree (\u53bb\u91cd)", "file_type": "document", "source_file": "ECC/docs/zh-CN/skills/clickhouse-io/SKILL.md", "source_location": "L52"}, {"id": "clickhouse_io_skill_aggregatingmergetree_\u9884\u805a\u5408", "label": "AggregatingMergeTree (\u9884\u805a\u5408)", "file_type": "document", "source_file": "ECC/docs/zh-CN/skills/clickhouse-io/SKILL.md", "source_location": "L68"}, {"id": "clickhouse_io_skill_\u67e5\u8be2\u4f18\u5316\u6a21\u5f0f", "label": "\u67e5\u8be2\u4f18\u5316\u6a21\u5f0f", "file_type": "document", "source_file": "ECC/docs/zh-CN/skills/clickhouse-io/SKILL.md", "source_location": "L95"}, {"id": "clickhouse_io_skill_\u9ad8\u6548\u8fc7\u6ee4", "label": "\u9ad8\u6548\u8fc7\u6ee4", "file_type": "document", "source_file": "ECC/docs/zh-CN/skills/clickhouse-io/SKILL.md", "source_location": "L97"}, {"id": "clickhouse_io_skill_\u805a\u5408", "label": "\u805a\u5408", "file_type": "document", "source_file": "ECC/docs/zh-CN/skills/clickhouse-io/SKILL.md", "source_location": "L117"}, {"id": "clickhouse_io_skill_\u7a97\u53e3\u51fd\u6570", "label": "\u7a97\u53e3\u51fd\u6570", "file_type": "document", "source_file": "ECC/docs/zh-CN/skills/clickhouse-io/SKILL.md", "source_location": "L142"}, {"id": "clickhouse_io_skill_\u6570\u636e\u63d2\u5165\u6a21\u5f0f", "label": "\u6570\u636e\u63d2\u5165\u6a21\u5f0f", "file_type": "document", "source_file": "ECC/docs/zh-CN/skills/clickhouse-io/SKILL.md", "source_location": "L160"}, {"id": "clickhouse_io_skill_\u6279\u91cf\u63d2\u5165_\u63a8\u8350", "label": "\u6279\u91cf\u63d2\u5165 (\u63a8\u8350)", "file_type": "document", "source_file": "ECC/docs/zh-CN/skills/clickhouse-io/SKILL.md", "source_location": "L162"}, {"id": "clickhouse_io_skill_\u6d41\u5f0f\u63d2\u5165", "label": "\u6d41\u5f0f\u63d2\u5165", "file_type": "document", "source_file": "ECC/docs/zh-CN/skills/clickhouse-io/SKILL.md", "source_location": "L201"}, {"id": "clickhouse_io_skill_\u7269\u5316\u89c6\u56fe", "label": "\u7269\u5316\u89c6\u56fe", "file_type": "document", "source_file": "ECC/docs/zh-CN/skills/clickhouse-io/SKILL.md", "source_location": "L219"}, {"id": "clickhouse_io_skill_\u5b9e\u65f6\u805a\u5408", "label": "\u5b9e\u65f6\u805a\u5408", "file_type": "document", "source_file": "ECC/docs/zh-CN/skills/clickhouse-io/SKILL.md", "source_location": "L221"}, {"id": "clickhouse_io_skill_\u6027\u80fd\u76d1\u63a7", "label": "\u6027\u80fd\u76d1\u63a7", "file_type": "document", "source_file": "ECC/docs/zh-CN/skills/clickhouse-io/SKILL.md", "source_location": "L248"}, {"id": "clickhouse_io_skill_\u67e5\u8be2\u6027\u80fd", "label": "\u67e5\u8be2\u6027\u80fd", "file_type": "document", "source_file": "ECC/docs/zh-CN/skills/clickhouse-io/SKILL.md", "source_location": "L250"}, {"id": "clickhouse_io_skill_\u8868\u7edf\u8ba1\u4fe1\u606f", "label": "\u8868\u7edf\u8ba1\u4fe1\u606f", "file_type": "document", "source_file": "ECC/docs/zh-CN/skills/clickhouse-io/SKILL.md", "source_location": "L270"}, {"id": "clickhouse_io_skill_\u5e38\u89c1\u5206\u6790\u67e5\u8be2", "label": "\u5e38\u89c1\u5206\u6790\u67e5\u8be2", "file_type": "document", "source_file": "ECC/docs/zh-CN/skills/clickhouse-io/SKILL.md", "source_location": "L286"}, {"id": "clickhouse_io_skill_\u65f6\u95f4\u5e8f\u5217\u5206\u6790", "label": "\u65f6\u95f4\u5e8f\u5217\u5206\u6790", "file_type": "document", "source_file": "ECC/docs/zh-CN/skills/clickhouse-io/SKILL.md", "source_location": "L288"}, {"id": "clickhouse_io_skill_\u6f0f\u6597\u5206\u6790", "label": "\u6f0f\u6597\u5206\u6790", "file_type": "document", "source_file": "ECC/docs/zh-CN/skills/clickhouse-io/SKILL.md", "source_location": "L320"}, {"id": "clickhouse_io_skill_\u961f\u5217\u5206\u6790", "label": "\u961f\u5217\u5206\u6790", "file_type": "document", "source_file": "ECC/docs/zh-CN/skills/clickhouse-io/SKILL.md", "source_location": "L341"}, {"id": "clickhouse_io_skill_\u6570\u636e\u6d41\u6c34\u7ebf\u6a21\u5f0f", "label": "\u6570\u636e\u6d41\u6c34\u7ebf\u6a21\u5f0f", "file_type": "document", "source_file": "ECC/docs/zh-CN/skills/clickhouse-io/SKILL.md", "source_location": "L361"}, {"id": "clickhouse_io_skill_etl_\u6a21\u5f0f", "label": "ETL \u6a21\u5f0f", "file_type": "document", "source_file": "ECC/docs/zh-CN/skills/clickhouse-io/SKILL.md", "source_location": "L363"}, {"id": "clickhouse_io_skill_\u53d8\u66f4\u6570\u636e\u6355\u83b7_cdc", "label": "\u53d8\u66f4\u6570\u636e\u6355\u83b7 (CDC)", "file_type": "document", "source_file": "ECC/docs/zh-CN/skills/clickhouse-io/SKILL.md", "source_location": "L387"}, {"id": "clickhouse_io_skill_\u6700\u4f73\u5b9e\u8df5", "label": "\u6700\u4f73\u5b9e\u8df5", "file_type": "document", "source_file": "ECC/docs/zh-CN/skills/clickhouse-io/SKILL.md", "source_location": "L411"}, {"id": "clickhouse_io_skill_1_\u5206\u533a\u7b56\u7565", "label": "1. \u5206\u533a\u7b56\u7565", "file_type": "document", "source_file": "ECC/docs/zh-CN/skills/clickhouse-io/SKILL.md", "source_location": "L413"}, {"id": "clickhouse_io_skill_2_\u6392\u5e8f\u952e", "label": "2. \u6392\u5e8f\u952e", "file_type": "document", "source_file": "ECC/docs/zh-CN/skills/clickhouse-io/SKILL.md", "source_location": "L419"}, {"id": "clickhouse_io_skill_3_\u6570\u636e\u7c7b\u578b", "label": "3. \u6570\u636e\u7c7b\u578b", "file_type": "document", "source_file": "ECC/docs/zh-CN/skills/clickhouse-io/SKILL.md", "source_location": "L425"}, {"id": "clickhouse_io_skill_4_\u907f\u514d", "label": "4. \u907f\u514d", "file_type": "document", "source_file": "ECC/docs/zh-CN/skills/clickhouse-io/SKILL.md", "source_location": "L431"}, {"id": "clickhouse_io_skill_5_\u76d1\u63a7", "label": "5. \u76d1\u63a7", "file_type": "document", "source_file": "ECC/docs/zh-CN/skills/clickhouse-io/SKILL.md", "source_location": "L438"}], "edges": [{"source": "c_users_rabin_documents_alsadeal_master_ecc_docs_zh_cn_skills_clickhouse_io_skill_md", "target": "clickhouse_io_skill_clickhouse_\u5206\u6790\u6a21\u5f0f", "relation": "contains", "confidence": "EXTRACTED", "source_file": "ECC/docs/zh-CN/skills/clickhouse-io/SKILL.md", "source_location": "L7", "weight": 1.0}, {"source": "clickhouse_io_skill_clickhouse_\u5206\u6790\u6a21\u5f0f", "target": "clickhouse_io_skill_\u4f55\u65f6\u6fc0\u6d3b", "relation": "contains", "confidence": "EXTRACTED", "source_file": "ECC/docs/zh-CN/skills/clickhouse-io/SKILL.md", "source_location": "L11", "weight": 1.0}, {"source": "clickhouse_io_skill_clickhouse_\u5206\u6790\u6a21\u5f0f", "target": "clickhouse_io_skill_\u6982\u8ff0", "relation": "contains", "confidence": "EXTRACTED", "source_file": "ECC/docs/zh-CN/skills/clickhouse-io/SKILL.md", "source_location": "L20", "weight": 1.0}, {"source": "clickhouse_io_skill_clickhouse_\u5206\u6790\u6a21\u5f0f", "target": "clickhouse_io_skill_\u8868\u8bbe\u8ba1\u6a21\u5f0f", "relation": "contains", "confidence": "EXTRACTED", "source_file": "ECC/docs/zh-CN/skills/clickhouse-io/SKILL.md", "source_location": "L32", "weight": 1.0}, {"source": "clickhouse_io_skill_\u8868\u8bbe\u8ba1\u6a21\u5f0f", "target": "clickhouse_io_skill_mergetree_\u5f15\u64ce_\u6700\u5e38\u7528", "relation": "contains", "confidence": "EXTRACTED", "source_file": "ECC/docs/zh-CN/skills/clickhouse-io/SKILL.md", "source_location": "L34", "weight": 1.0}, {"source": "clickhouse_io_skill_\u8868\u8bbe\u8ba1\u6a21\u5f0f", "target": "clickhouse_io_skill_replacingmergetree_\u53bb\u91cd", "relation": "contains", "confidence": "EXTRACTED", "source_file": "ECC/docs/zh-CN/skills/clickhouse-io/SKILL.md", "source_location": "L52", "weight": 1.0}, {"source": "clickhouse_io_skill_\u8868\u8bbe\u8ba1\u6a21\u5f0f", "target": "clickhouse_io_skill_aggregatingmergetree_\u9884\u805a\u5408", "relation": "contains", "confidence": "EXTRACTED", "source_file": "ECC/docs/zh-CN/skills/clickhouse-io/SKILL.md", "source_location": "L68", "weight": 1.0}, {"source": "clickhouse_io_skill_clickhouse_\u5206\u6790\u6a21\u5f0f", "target": "clickhouse_io_skill_\u67e5\u8be2\u4f18\u5316\u6a21\u5f0f", "relation": "contains", "confidence": "EXTRACTED", "source_file": "ECC/docs/zh-CN/skills/clickhouse-io/SKILL.md", "source_location": "L95", "weight": 1.0}, {"source": "clickhouse_io_skill_\u67e5\u8be2\u4f18\u5316\u6a21\u5f0f", "target": "clickhouse_io_skill_\u9ad8\u6548\u8fc7\u6ee4", "relation": "contains", "confidence": "EXTRACTED", "source_file": "ECC/docs/zh-CN/skills/clickhouse-io/SKILL.md", "source_location": "L97", "weight": 1.0}, {"source": "clickhouse_io_skill_\u67e5\u8be2\u4f18\u5316\u6a21\u5f0f", "target": "clickhouse_io_skill_\u805a\u5408", "relation": "contains", "confidence": "EXTRACTED", "source_file": "ECC/docs/zh-CN/skills/clickhouse-io/SKILL.md", "source_location": "L117", "weight": 1.0}, {"source": "clickhouse_io_skill_\u67e5\u8be2\u4f18\u5316\u6a21\u5f0f", "target": "clickhouse_io_skill_\u7a97\u53e3\u51fd\u6570", "relation": "contains", "confidence": "EXTRACTED", "source_file": "ECC/docs/zh-CN/skills/clickhouse-io/SKILL.md", "source_location": "L142", "weight": 1.0}, {"source": "clickhouse_io_skill_clickhouse_\u5206\u6790\u6a21\u5f0f", "target": "clickhouse_io_skill_\u6570\u636e\u63d2\u5165\u6a21\u5f0f", "relation": "contains", "confidence": "EXTRACTED", "source_file": "ECC/docs/zh-CN/skills/clickhouse-io/SKILL.md", "source_location": "L160", "weight": 1.0}, {"source": "clickhouse_io_skill_\u6570\u636e\u63d2\u5165\u6a21\u5f0f", "target": "clickhouse_io_skill_\u6279\u91cf\u63d2\u5165_\u63a8\u8350", "relation": "contains", "confidence": "EXTRACTED", "source_file": "ECC/docs/zh-CN/skills/clickhouse-io/SKILL.md", "source_location": "L162", "weight": 1.0}, {"source": "clickhouse_io_skill_\u6570\u636e\u63d2\u5165\u6a21\u5f0f", "target": "clickhouse_io_skill_\u6d41\u5f0f\u63d2\u5165", "relation": "contains", "confidence": "EXTRACTED", "source_file": "ECC/docs/zh-CN/skills/clickhouse-io/SKILL.md", "source_location": "L201", "weight": 1.0}, {"source": "clickhouse_io_skill_clickhouse_\u5206\u6790\u6a21\u5f0f", "target": "clickhouse_io_skill_\u7269\u5316\u89c6\u56fe", "relation": "contains", "confidence": "EXTRACTED", "source_file": "ECC/docs/zh-CN/skills/clickhouse-io/SKILL.md", "source_location": "L219", "weight": 1.0}, {"source": "clickhouse_io_skill_\u7269\u5316\u89c6\u56fe", "target": "clickhouse_io_skill_\u5b9e\u65f6\u805a\u5408", "relation": "contains", "confidence": "EXTRACTED", "source_file": "ECC/docs/zh-CN/skills/clickhouse-io/SKILL.md", "source_location": "L221", "weight": 1.0}, {"source": "clickhouse_io_skill_clickhouse_\u5206\u6790\u6a21\u5f0f", "target": "clickhouse_io_skill_\u6027\u80fd\u76d1\u63a7", "relation": "contains", "confidence": "EXTRACTED", "source_file": "ECC/docs/zh-CN/skills/clickhouse-io/SKILL.md", "source_location": "L248", "weight": 1.0}, {"source": "clickhouse_io_skill_\u6027\u80fd\u76d1\u63a7", "target": "clickhouse_io_skill_\u67e5\u8be2\u6027\u80fd", "relation": "contains", "confidence": "EXTRACTED", "source_file": "ECC/docs/zh-CN/skills/clickhouse-io/SKILL.md", "source_location": "L250", "weight": 1.0}, {"source": "clickhouse_io_skill_\u6027\u80fd\u76d1\u63a7", "target": "clickhouse_io_skill_\u8868\u7edf\u8ba1\u4fe1\u606f", "relation": "contains", "confidence": "EXTRACTED", "source_file": "ECC/docs/zh-CN/skills/clickhouse-io/SKILL.md", "source_location": "L270", "weight": 1.0}, {"source": "clickhouse_io_skill_clickhouse_\u5206\u6790\u6a21\u5f0f", "target": "clickhouse_io_skill_\u5e38\u89c1\u5206\u6790\u67e5\u8be2", "relation": "contains", "confidence": "EXTRACTED", "source_file": "ECC/docs/zh-CN/skills/clickhouse-io/SKILL.md", "source_location": "L286", "weight": 1.0}, {"source": "clickhouse_io_skill_\u5e38\u89c1\u5206\u6790\u67e5\u8be2", "target": "clickhouse_io_skill_\u65f6\u95f4\u5e8f\u5217\u5206\u6790", "relation": "contains", "confidence": "EXTRACTED", "source_file": "ECC/docs/zh-CN/skills/clickhouse-io/SKILL.md", "source_location": "L288", "weight": 1.0}, {"source": "clickhouse_io_skill_\u5e38\u89c1\u5206\u6790\u67e5\u8be2", "target": "clickhouse_io_skill_\u6f0f\u6597\u5206\u6790", "relation": "contains", "confidence": "EXTRACTED", "source_file": "ECC/docs/zh-CN/skills/clickhouse-io/SKILL.md", "source_location": "L320", "weight": 1.0}, {"source": "clickhouse_io_skill_\u5e38\u89c1\u5206\u6790\u67e5\u8be2", "target": "clickhouse_io_skill_\u961f\u5217\u5206\u6790", "relation": "contains", "confidence": "EXTRACTED", "source_file": "ECC/docs/zh-CN/skills/clickhouse-io/SKILL.md", "source_location": "L341", "weight": 1.0}, {"source": "clickhouse_io_skill_clickhouse_\u5206\u6790\u6a21\u5f0f", "target": "clickhouse_io_skill_\u6570\u636e\u6d41\u6c34\u7ebf\u6a21\u5f0f", "relation": "contains", "confidence": "EXTRACTED", "source_file": "ECC/docs/zh-CN/skills/clickhouse-io/SKILL.md", "source_location": "L361", "weight": 1.0}, {"source": "clickhouse_io_skill_\u6570\u636e\u6d41\u6c34\u7ebf\u6a21\u5f0f", "target": "clickhouse_io_skill_etl_\u6a21\u5f0f", "relation": "contains", "confidence": "EXTRACTED", "source_file": "ECC/docs/zh-CN/skills/clickhouse-io/SKILL.md", "source_location": "L363", "weight": 1.0}, {"source": "clickhouse_io_skill_\u6570\u636e\u6d41\u6c34\u7ebf\u6a21\u5f0f", "target": "clickhouse_io_skill_\u53d8\u66f4\u6570\u636e\u6355\u83b7_cdc", "relation": "contains", "confidence": "EXTRACTED", "source_file": "ECC/docs/zh-CN/skills/clickhouse-io/SKILL.md", "source_location": "L387", "weight": 1.0}, {"source": "clickhouse_io_skill_clickhouse_\u5206\u6790\u6a21\u5f0f", "target": "clickhouse_io_skill_\u6700\u4f73\u5b9e\u8df5", "relation": "contains", "confidence": "EXTRACTED", "source_file": "ECC/docs/zh-CN/skills/clickhouse-io/SKILL.md", "source_location": "L411", "weight": 1.0}, {"source": "clickhouse_io_skill_\u6700\u4f73\u5b9e\u8df5", "target": "clickhouse_io_skill_1_\u5206\u533a\u7b56\u7565", "relation": "contains", "confidence": "EXTRACTED", "source_file": "ECC/docs/zh-CN/skills/clickhouse-io/SKILL.md", "source_location": "L413", "weight": 1.0}, {"source": "clickhouse_io_skill_\u6700\u4f73\u5b9e\u8df5", "target": "clickhouse_io_skill_2_\u6392\u5e8f\u952e", "relation": "contains", "confidence": "EXTRACTED", "source_file": "ECC/docs/zh-CN/skills/clickhouse-io/SKILL.md", "source_location": "L419", "weight": 1.0}, {"source": "clickhouse_io_skill_\u6700\u4f73\u5b9e\u8df5", "target": "clickhouse_io_skill_3_\u6570\u636e\u7c7b\u578b", "relation": "contains", "confidence": "EXTRACTED", "source_file": "ECC/docs/zh-CN/skills/clickhouse-io/SKILL.md", "source_location": "L425", "weight": 1.0}, {"source": "clickhouse_io_skill_\u6700\u4f73\u5b9e\u8df5", "target": "clickhouse_io_skill_4_\u907f\u514d", "relation": "contains", "confidence": "EXTRACTED", "source_file": "ECC/docs/zh-CN/skills/clickhouse-io/SKILL.md", "source_location": "L431", "weight": 1.0}, {"source": "clickhouse_io_skill_\u6700\u4f73\u5b9e\u8df5", "target": "clickhouse_io_skill_5_\u76d1\u63a7", "relation": "contains", "confidence": "EXTRACTED", "source_file": "ECC/docs/zh-CN/skills/clickhouse-io/SKILL.md", "source_location": "L438", "weight": 1.0}], "input_tokens": 0, "output_tokens": 0}